[
  {
    "Content": [
      {
        "h": [
          {
            "h": [
              "Commune de Nivelles", 
              {
                "h": [
                  "Conseil communal", 
                  {
                    "p": [
                      "www.nivelles.be, le lundi 7 décembre 2015 à 11-12 heures", 
                      "Ordre du jour de la séance du Conseil communal du 23 novembre 2015"
                    ]
                  }
                ]
              }
            ]
          }
        ]
      }, 
      {
        "h": [
          "Invitation à la séance du lundi 23 novembre 2015 à 20 heures 00", 
          {
            "p": [
              "Hôtel de Ville  Salle des Mariages - Place Albert 1er - 1400 Nivelles"
            ]
          }, 
          {
            "-h": [
              "Séance publique", 
              {
                "h": [
                  {
                    "li class=\"obj\"": [
                      "1. Approbation du procès-verbal de la séance du Conseil du 26 octobre 2015", 
                      "2. Communications diverses", 
                      "3. Ordonnances de police:", 
                      {
                        "li class=\"obj\"": [
                          "a) Règlement général de police administrative", 
                          "b) Règlement général de police environnementale", 
                          "c) Règlement général de police - stationnement", 
                          "d) Règlement général de police - voirie"
                        ]
                      }, 
                      "4. Règlement prévention incendie", 
                      "5. Règlement d'Ordre Intérieur du Conseil communal - modifications", 
                      "6. Renouvellement de la convention pour l'engagement d'un médiateur SAC", 
                      "7. Contrat de gestion - rapport d'évaluation exercice 2014 - examen des recettes et des dépenses:", 
                      {
                        "li class=\"obj\"": [
                          "a) Maison des Sports", 
                          "b) Nivelles Entreprises", 
                          "c) Nivelles en Fêtes", 
                          "d) Nivelles Commerces", 
                          "e) Centre Culturel", 
                          "f) Promo Lecture", 
                          "g) Maison du Tourisme", 
                          "h) Office du Tourisme", 
                          "i) Centre Nivellois de la Petite Enfance", 
                          "j) Maison des Enfants"
                        ]
                      }, 
                      "8. ORES - Assemblée générale du 18/12/2015", 
                      "9. SEDIFIN - Assemblée générale ordinaire et extraordinaire du 08/12/2015", 
                      "10. IBW - Assemblée générale ordinaire du 08/12/2015", 
                      "11. ISBW - Assemblée générale extraordinaire du 14/12/2015", 
                      "12. ARRETES DE POLICE:", 
                      {
                        "li class=\"obj\"": [
                          "a) Avenue du Centenaire, 6 - règlement complémentaire sur la police de la circulation routière relatif à la création de 1 emplacement de stationnement réservé aux personnes handicapées", 
                          "b) Rue de Copenhague, 1 - règlement complémentaire sur la police de circulation routière relatif à la création de 1 emplacement de stationnement réservé aux personnes handicapées", 
                          "c) Allée des Coquelicots, 37 - règlement complémentaire sur la police de la circulation routière relatif à la création de 1 emplacement de stationnement réservé aux personnes handicapées", 
                          "d) RN27/N27a - Carrefours formés par la RN27 (Faubourg de Bruxelles, Boulevard Fleur de Lys), la RN27a (Boulevard des Archers) la rue de Bruxelles et la rue Chambille - règlement complémentaire sur la police de la circulation routière - Approbation du projet d'Arrêté ministériel relatif à la signalisation lumineuse tricolore"
                        ]
                      }
                    ]
                  }, 
                  "FINANCES", 
                  {
                    "li class=\"obj\"": [
                      "13. Demandes de subside pour 2015:", 
                      {
                        "li class=\"obj\"": [
                          "a) ASBL Du Côté des Champs", 
                          "b) ASBL Lire et Ecrire", 
                          "c) ASBL Runbox Evenements", 
                          "d) ASBL Royal Judo Club", 
                          "e) ASBL Kayak Club", 
                          "f) ASBL Makoto Karaté Club", 
                          "g) ASBL CYANA", 
                          "h) ASBL Royal Pingouin Hockey Club", 
                          "i) ASBL Royal Nautic Club Nivellois", 
                          "j) ASBL Elan Nivellois", 
                          "k) Société Royale Les Archers de Nivelles", 
                          "l) Comité de quartier Objectif Bornival", 
                          "m) Association Consoeurie des Secrets de Dame Gertrude", 
                          "n) Fédération scouts de Belgique - Unité Sainte Gertrude"
                        ]
                      }, 
                      "14. Centimes additionnels au précompte immobilier", 
                      "15. Taxe additionnelle communale à l'impôt des personnes physiques", 
                      "16. Règlement sur la taxe communale additionnelle à la taxe régionale sur les pylônes"
                    ]
                  }, 
                  "TRAVAUX", 
                  {
                    "li class=\"obj\"": [
                      "17. Marché de travaux - Approbation d'avenant 3: Remplacement des toitures et bardages de la piscine communale", 
                      "18. Marché de travaux - Approbation des conditions et du mode de passation: Désamiantage des calorifuges au plâtre et amiante des conduites de chauffage, mise en peinture des murs, sol et plafond de la chaufferie de l'Hôtel de Ville", 
                      "19. Marchés de fournitures - Approbation des conditions et du mode de passation:", 
                      {
                        "li class=\"obj\"": [
                          "a) Acquisition de mobilier pour l'Ecole André Hecq", 
                          "b) Acquisition de mobilier pour la cellule de médiation"
                        ]
                      }
                    ]
                  }, 
                  "PATRIMOINE", 
                  {
                    "li class=\"obj\"": [
                      "20. Marché de services - Approbation des conditions et du mode de passation: Extension de la mission de géomètre en vue de dresser le plan définitif et de borner la voirie de l'allée des Sources à Monstreux"
                    ]
                  }, 
                  "URBANISME", 
                  {
                    "li class=\"obj\"": [
                      "21. Chemin communal n°19 - accès donné à une habitation unifamiliale - dénomination de la voirie", 
                      "22. Modification de la voirie communale dans le cadre d'un projet d'urbanisme - site établi Rue de Bruxelles - Rue St André - Rue des Frères Piersaux"
                    ]
                  }, 
                  "AFFAIRES SOCIALES", 
                  {
                    "li class=\"obj\"": [
                      "23. CPAS - Modification Budgétaire extraordinaire n°2"
                    ]
                  }, 
                  "QUESTIONS D'ACTUALITE", 
                  {
                    "li class=\"obj\"": [
                      "a) Eglise Sainte Marguerite à Thines - réparation du chauffage en panne", 
                      "b) Travaux sur le parking rue Saint Georges", 
                      "c) Jean de Nivelles - problème de fonctionnement", 
                      "d) Tronçon de la rue du Paradis entre l'Ipet et la Chée de Hal - problème de circulation"
                    ]
                  }
                ]
              }, 
              "Séance à huis clos", 
              {
                "h": [
                  {
                    "li class=\"obj\"": [
                      "1. ASBL Maison du Tourisme du Roman Païs - Prise d'acte de la démission d'un délégué de la Ville de Nivelles et désignation d'un remplaçant", 
                      "2. ASBL Agence Locale de l'Emploi - Prise d'acte de la démission d'un délégué de la Ville de Nivelles et désignation d'un remplaçant", 
                      "3. ASBL Nivelles en Fêtes - Prise d'acte de la démission d'un administrateur et désignation d'un remplaçant", 
                      "4. ASBL Nivelles en Fêtes - Prise d'acte de la démission d'un administrateur et désignation d'un remplaçant"
                    ]
                  }, 
                  "ENSEIGNEMENT", 
                  {
                    "li class=\"obj\"": [
                      "5. ANDRE HECQ ", 
                      {
                        "li": [
                          "Ratification désignation au 01/09/2015 d'une institutrice primaire à titre temporaire - 6 périodes/semaine en remplacement d'une institutrice en congé pour accident du travail ", 
                          "Ratification désignation au 22/09/2015 d'une institutrice primaire à titre temporaire - 19 périodes/semaine - en remplacement d'une institutrice en congé de maladie ", 
                          "Ratification cessation de fonctions au 28.09.2015 d'une institutrice primaire à titre temporaire - 19 périodes/semaine - désignée en remplacement d'une institutrice en congé de maladie ", 
                          "Ratification désignation au 01/09/2015 d'une institutrice maternelle à titre temporaire - 5 périodes/semaine en remplacement d'une institutrice en interruption de carrière partielle (pour 2P) et en congé pour accident du travail (pour 3 P)", 
                          "Ratification désignation au 01/09/2015 d'une institutrice primaire à titre temporaire - 6 périodes/semaine en remplacement d'une institutrice en congé pour accident du travail ", 
                          "Ratification désignation au 01/09/2015 d'une institutrice maternelle à titre temporaire - 18 périodes/semaine en remplacement d'une institutrice en congé pour accident du travail ", 
                          "Ratification désignation au 01/09/2015 d'une institutrice maternelle à titre temporaire - temps plein dans un emploi vacant ", 
                          "Ratification désignation au 01/09/2015 d'une institutrice primaire à titre temporaire - temps plein dans un emploi vacant ", 
                          "Ratification désignation au 01/09/2015 d'une institutrice primaire à titre temporaire - 6 périodes/semaine en remplacement d'une institutrice en congé pour accident du travail ", 
                          "Ratification désignation au 01/09/2015 d'une puéricultrice APE - Fédération Wallonie - Bruxelles - 4/5ème temps - Convention RW EN-06464 - Poste RW FOB 022", 
                          "Ratification désignation au 01/09/2015 d'une institutrice primaire à titre temporaire - 6 périodes/semaine en remplacement d'une institutrice en congé pour accident du travail", 
                          "Ratification désignation au 01/09/2015 d'une institutrice primaire APE - Fédération Wallonie - Bruxelles - 12 périodes/semaine - Convention RW EN-06464 - Poste RW FOB 372b", 
                          "Ratification désignation au 01/09/2015 d'une institutrice primaire à titre temporaire - 17 périodes/semaine en remplacement de 2 institutrices en congé pour prestations réduites (10 P), d'une institutrice en interruption de carrière partielle (5 P) et dans un emploi vacant (2 P) Ratification désignation au 01/09/2015 d'une institutrice maternelle à titre temporaire - temps plein en remplacement de 2 institutrices en congé pour prestations réduites (10 P), d'une institutrice en interruption de carrière partielle (3 P) et dans un emploi vancant (13 P)", 
                          "Ratification désignation au 01/09/2015 d'un maître spécial de langues à titre temporaire - 8 périodes/semaine"
                        ]
                      }, 
                      "6. MAILLEBOTTE ", 
                      {
                        "li": [
                          "Ratification désignation au 01/09/2015 d'une institutrice primaire à titre temporaire - temps plein - en remplacement d'une institutrice en congé pour mission ", 
                          "Ratification désignation au 01/09/2015 d'une puéricultrice APE - Fédération Wallonie - Bruxelles - 4/5ème temps - Convention RW EN-06464 - Poste RW FOB 030", 
                          "Ratification désignation au 01/09/2015 d'un maître spécial de religion protestante à titre temporaire - 2 périodes/semaine ", 
                          "Ratification désignation au 01/09/2015 d'un maître spécial de religion catholique à titre temporaire - 12 périodes/semaine - en remplacement d'une institutrice en congé pour accident du travail ", 
                          "Ratification désignation au 01/09/2015 d'une institutrice maternelle à titre temporaire - 21 périodes/semaine en remplacement d'une institutrice en DPPR type IV, d'une institutrice en congé pour prestations réduites, de 2 institutrices en interruption de carrière partielle durant l'année scolaire 2015-2016 Ratification désignation au 01/09/2015 d'une institutrice primaire à titre temporaire - temps plein en remplacement d'une institutrice en congé pour mission Ratification désignation au 01/09/2015 d'une institutrice primaire à titre temporaire - temps plein en remplacement d'une institutrice en congé pour prestations réduites (pour 3 P) et dans un emploi vacant (pour 21 P) Ratification désignation au 01/09/2015 d'un maître spécial de morale à titre temporaire - 12 périodes/semaine Ratification désignation au 03/09/2015 d'une institutrice maternelle à titre temporaire - 20 périodes/semaine en remplacement d'une institutrice en congé de maladie Ratification désignation au 01/09/2015 d'une institutrice primaire à titre temporaire - temps plein Ratification désignation au 01/09/2015 d'une institutrice primaire à titre temporaire - 7 périodes/semaine en remplacement d'une institutrice en congé pour prestations réduites ( 2 P) et d'une institutrice en interruption de carrière partielle (5 P) Ratification désignation au 01/09/2015 d'une institutrice primaire à titre temporaire - temps plein Ratification désignation au 01/09/2015 d'un maître spécial de langues à titre temporaire - 2 périodes/semaine"
                        ]
                      }, 
                      "7. BORNIVAL ", 
                      {
                        "li": [
                          "Ratification désignation au 01/09/2015 d'un maître spécial de religion islamique à titre temporaire - 2 périodes/semaine ", 
                          "Ratification désignation au 01/09/2015 d'une institutrice primaire à titre temporaire - temps plein ", 
                          "Ratification désignation au 01/09/2015 d'un instituteur maternel à titre temporaire - temps plein ", 
                          "Ratification désignation au 01/09/2015 d'une institutrice primaire à titre temporaire - temps plein ", 
                          "Ratification désignation au 01/09/2015 d'une institutrice primaire à titre temporaire - temps plein"
                        ]
                      }, 
                      "8. ANDRE HECQ - MAILLEBOTTE", 
                      {
                        "li": [
                          "Ratification désignation au 01/09/2015 d'un maître spécial de psychomotricité à titre temporaire 9 périodes/semaine ", 
                          "Ratification désignation au 01/09/2015 d'un maître spécial d'éducation physique à titre temporaire - 20 périodes/semaine - en remplacement d'une institutrice en congé pour prestations réduites (12 P) et dans un emploi vacant (8 P)"
                        ]
                      }, 
                      "9. ANDRE HECQ - BORNIVAL ", 
                      {
                        "li": [
                          "Ratification désignation au 01/09/2015 d'une institutrice primaire à titre temporaire -19 périodes/semaine (14 périodes dans un emploi vacant et 5 périodes en remplacement d'une institutrice en interruption de carrière partielle durant l'année scolaire 2015-2016) Ratification désignation au 01/09/2015 d'un maître spécial de morale à titre temporaire - 18 périodes/semaine Ratification désignation au 01/09/2015 d'un maître spécial d'éducation physique à titre temporaire - 20 périodes/semaine Ratification désignation au 01/09/2015 d'un maître spécial de religion catholique à titre temporaire - 16 périodes/semaine"
                        ]
                      }, 
                      "10. MAILLEBOTTE - BORNIVAL ", 
                      {
                        "li": [
                          "Ratification désignation au 01/09/2015 d'un maître spécial de psychomotricité à titre temporaire - 4 périodes/semaine"
                        ]
                      }, 
                      "11. ANDRE HECQ - MAILLEBOTTE - BORNIVAL ", 
                      {
                        "li": [
                          "Ratification désignation au 01/09/2014 d'un maître spécial de psychomotricité - APE Fédération Wallonie-Bruxelles - Convention RW EN - 06464 - Poste APE RW FOB 459a- 13 périodes/semaine"
                        ]
                      }, 
                      "12. ACADEMIE ", 
                      {
                        "li": [
                          "Ratification octroi d'un congé pour exercer une autre fonction dansl'enseignement à un professeur chargé de l'accompagnement, 2 périodes/semaine, du 28/09/15 au 30/06/16 ", 
                          "Ratification octroi d'un congé pour exercer une autre fonction dansl'enseignement à un professeur d'accordéon, 6 périodes/semaine, du 15/09/15 au 30/06/16 ", 
                          "Ratification octroi d'un congé pour exercer une autre fonction dansl'enseignement à un professeur de diction-déclamation 12 périodes/semaine, du 01/09/15 au 30/06/16 ", 
                          "Ratification octroi d'un congé pour exercer une autre fonction dansl'enseignement à un professeur de diction-déclamation 2 périodes/semaine, du 01/09/15 au 30/06/16 ", 
                          "Ratification désignation d'un professeur d'art dramatique, dans un emploi temporaire non vacant 1 période/semaine et dans un emploi temporaire 7 périodes/semaine, du 05/10/15 jusqu'au retour de la titulaire en congé de maternité Ratification désignation d'un professeur de diction-déclamation, dans un emploi temporaire non vacant 1 période/semaine et dans un emploi temporaire 2 périodes/semaine, du 05/10/15 jusqu'au retour de la titulaire en congé de maternité Ratification désignation d'un secrétaire-surveillant dans un emploi temporaire 12 heures/semaine, du 01/09/15 au 30/06/16 Ratification désignation d'un professeur de piano dans un emploi temporaire non vacant 12 périodes/semaine du 01/10/15 au 31/05/16 Ratification désignation d'un professeur de piano, dans un emploi temporaire vacant 2 périodes/semaine , du 28/09/15 au 30/06/16 Ratification désignation d'un professeur de piano, dans un emploi temporaire 20 périodes/semaine , du 01/09/15 au 30/06/16 Ratification désignation d'un professeur de percussions dans un emploi temporaire 6 périodes/semaine , du 01/09/15 au 30/06/16 Ratification désignation d'un professeur de flûte traversière, dans un emploi temporaire non vacant 2 périodes/semaine , du 28/09/15 au 30/06/16 Ratification désignation d'un professeur de guitare, dans un emploi temporaire 9 périodes/semaine , du 01/09/15 au 14/09/15 Ratification désignation d'un professeur de guitare, dans un emploi temporaire 7 périodes/semaine , du 15/09/15 au 30/06/16 Ratification désignation d'un professeur de guitare, dans un emploi temporaire non vacant 2 périodes/semaine , du 15/09/15 au 30/06/16 Ratification désignation d'un professeur de flûte traversière, dans un emploi temporaire non vacant 1 période/semaine , du 26/09/15 au 30/06/16 Ratification désignation d'un professeur de guitare, dans un emploi temporaire 6 périodes/semaine , du 01/09/15 au 30/06/16 Ratification désignation d'un professeur d'art dramatique, dans un emploi temporaire non vacant 6 périodes/semaine du 05/10/15 jusqu'au retour de la titulaire en congé de maternité Ratification désignation d'un professeur de diction-déclamation, dans un emploi temporaire non vacant 4 périodes/semaine, du 05/10/15 jusqu'au retour de la titulaire en congé de maternité Ratification désignation d'un professeur de formation pluridisciplinaire dans le domaine des arts de la parole, dans un emploi temporaire non vacant 4 périodes/semaine, du 05/10/15 jusqu'au retour de la titulaire en congé de maternité Ratification désignation d'un professeur chargé de l'accompagnement, dans un emploi temporaire 1 période/semaine, du 01/09/15 au 30/06/16 Ratification désignation d'un professeur de piano dans un emploi temporaire 3 périodes/semaine du 01/09/15 au 30/16/16 Ratification désignation d'un professeur de formation pluridisciplinaire dans le domaine des arts de la parole, dans un emploi temporaire non vacant 12 périodes/semaine, du 01/09/15 au 30/06/16 Ratification désignation d'un professeur de formation générale jazz, dans un emploi temporaire non vacant 1 période/semaine, du 15/09/15 au 30/06/16 Ratification désignation d'un professeur de formation instrumentale et ensemble jazz-spécialité Vents, dans un emploi temporaire non vacant 1 période/semaine, du 15/09/15 au 30/06/16 Ratification désignation d'une secrétaire dans un emploi temporaire 19 heures/semaine, du 01/09/15 au 30/06/16 Ratification désignation d'un professeur d'art dramatique, dans un emploi temporaire 7 périodes/semaine du 01/09/15 au 30/06/16 Ratification désignation d'un professeur de diction-déclamation, dans un emploi temporaire 2 périodes/semaine et dans un emploi temporaire non vacant, 5 périodes/semaine du 01/09/15 au 30/06/16 Ratification désignation d'un professeur de formation pluridisciplinaire dans le domaine des arts de la parole dans un emploi temporaire non vacant, 4 périodes/semaine du 01/09/15 au 30/06/16 Ratification désignation d'un professeur de formation pluridisciplinaire dans le domaine des arts plastiques dans un emploi temporaire 21 périodes/semaine du 01/09/15 au 30/06/16 Ratification désignation d'un professeur de violon dans un emploi temporaire 7 périodes/semaine du 01/09/15 au 30/06/16 Ratification désignation d'un professeur de clavecin dans un emploi temporaire vacant 2 périodes/semaine du 02/10/15 au 30/06/16 Ratification désignation d'un professeur de danse classique dans un emploi temporaire 3 périodes/semaine du 01/09/15 au 30/06/16 Ratification désignation d'un professeur d'ensemble instrumental dans un emploi temporaire 1 période/semaine du 01/09/15 au 30/06/16 Ratification désignation d'un professeur de trompette dans un emploi temporaire 6 périodes/semaine du 01/09/15 au 14/09/15", 
                          "Ratification désignation d'un professeur de trompette dans un emploi temporaire 4 périodes/semaine du 15/09/15 au 30/06/16", 
                          "Ratification désignation d'un professeur de trompette dans un emploi temporaire non vacant 2 périodes/semaine du 15/09/15 au 30/06/16 ", 
                          "Ratification désignation d'un professeur de trompette dans un emploi temporaire non vacant 1 période/semaine du 28/09/15 au 30/06/16 ", 
                          "Ratification désignation d'un professeur de formation pluridisciplinaire dans le domaine des arts plastiques dans un emploi temporaire 7 périodes/semaine du 01/09/15 au 30/06/16 ", 
                          "Ratification désignation d'un professeur de guitare, dans un emploi temporaire 4 périodes/semaine , du 01/09/15 au 30/06/16 ", 
                          "Ratification désignation d'un professeur de formation pluridisciplinaire dans le domaine des arts de la parole, dans un emploi temporaire non vacant 2 périodes/semaine, du 01/09/15 au 30/06/16 ", 
                          "Ratification désignation d'un professeur de violon alto, dans un emploi temporaire non vacant 8 périodes/semaine, du 25/09/15 au 25/10/15 ", 
                          "Ratification désignation d'un professeur d'ensemble instrumental, dans un emploi temporaire non vacant 2 périodes/semaine, du 25/09/15 au 25/10/15 ", 
                          "Ratification désignation d'un professeur de violoncelle dans un emploi temporaire 3 périodes/semaine du 01/09/15 au 30/06/16", 
                          "Ratification désignation d'un professeur de formation pluridisciplinaire dans le domaine des arts de la parole, dans un emploi temporaire non vacant 1 période/semaine et dans un emploi temporaire vacant, 3 périodes/semaine, du 01/09/15 au 30/06/16 Ratification désignation d'un professeur d'art dramatique, dans un emploi temporaire vacant 1 période/semaine , du 01/09/15 au 30/06/16 Ratification désignation d'un professeur d'accordéon, dans un emploi temporaire non vacant 2 périodes/semaine, du 14/09/15 au 30/06/16 Ratification désignation d'un professeur d'accordéon, dans un emploi temporaire 4 périodes/semaine, du 14/09/15 au 30/06/16", 
                          "Ratification désignation d'un professeur chargé de l'accompagnement, dans un emploi temporaire non vacant 2 périodes/semaine, du 01/10/15 au 30/06/16", 
                          "Désignation d'un professeur de trompette dans un emploi temporaire non vacant 3 périodes/semaine du 15/09/15 au 30/06/16", 
                          "Désignation d'un professeur d'accordéon dans un emploi temporaire non vacant 2 périodes/semaine du 26/09/15 jusqu'au retour de la titulaire, en congé de maladie", 
                          "Désignation d'un professeur de formation musicale dans un emploi temporaire non vacant, 1 période/semaine, du 26/10/15 jusqu'au retour de la titulaire, en interruption de carrière", 
                          "Désignation d'un professeur de formation musicale dans un emploi temporaire non vacant, 2 périodes/semaine, du 26/10/15 jusqu'au retour de la titulaire, en interruption de carrière", 
                          "Désignation d'un professeur de formation musicale dans un emploi temporaire non vacant, 2 périodes/semaine, du 26/10/15 jusqu'au retour de la titulaire, en interruption de carrière", 
                          "Annulation de la délibération du conseil communal du 22 juin 2015 octroyant un congé pour interruption de carrière dans le cadre du congé parental, de 11 périodes/semaine, du 01/10/15 au 31/05/16. Nouvelle délibération octroyant un congé pour interruption de carrière dans le cadre du congé parental, de 12 périodes/semaine, du 01/10/15 au 31/05/16", 
                          "Octroi d'un congé pour interruption de carrière dans le cadre du congé parental, de 8 périodes/semaine, du 26/10/15 au 25/06/16 à un professeur de formation musicale et de violon"
                        ]
                      }
                    ]
                  }
                ]
              }
            ], 
            "h": [
              "Ordre du jour"
            ]
          }
        ]
      }
    ]
  }, 
  {
    "Enveloppe": [
      {
        "id_ddr": "2015-11-23T20-00_gWbrCmnNivelles-clg-3_consCmn-seancePublique-4_odj-4"
      }, 
      {
        "Stamps": [
          {
            "op_tpl:": [
              "web_detect", 
              "web_grab", 
              "web_remove", 
              "email_delivery", 
              "email_sended", 
              "pmail_delivery", 
              "pmail_sended", 
              "doc_creation", 
              "doc_signature", 
              "add_content_silocanceled_with_notification", 
              "canceled_without_notification"
            ]
          }, 
          {
            "Stamp": [
              {
                "op": "web_detect"
              }, 
              {
                "dt": "2015-12-07T12-01"
              }, 
              {
                "authors": "Installé Patrick 2013 - ddr_create_event_entry.py"
              }, 
              {
                "ref": "www.nivelles.be/content/seance"
              }, 
              {
                "note": ""
              }
            ]
          }, 
          {
            "Stamp": [
              {
                "op": "web_grab"
              }, 
              {
                "dt": "2015-12-07T23:30"
              }, 
              {
                "authors": "Installé Patrick 2013 - ddr_create_event_entry.py"
              }, 
              {
                "ref": "http://www.nivelles.be/content/ordre-du-jour-seance-du-conseil-communal-du-23-novembre-2015"
              }, 
              {
                "note": ""
              }
            ]
          }, 
          {
            "Stamp": [
              {
                "op": "add_content_silo"
              }, 
              {
                "dt": "2015-12-07T23:30"
              }, 
              {
                "authors": "Installé Patrick 2013 - ddr_create_event_entry.py"
              }, 
              {
                "ref": ""
              }, 
              {
                "note": "from_institution"
              }
            ]
          }, 
          {
            "Stamp": [
              {
                "op": "web_ddr_doc_dw"
              }, 
              {
                "dt": "2015-12-07T23:30"
              }, 
              {
                "authors": "Installé Patrick 2013 - ddr_create_event_entry.py"
              }, 
              {
                "ref": "http://tinyurl.com/nrdbqu3"
              }, 
              {
                "note": "from_web"
              }
            ]
          }
        ]
      }
    ]
  }, 
  {
    "Metadata": [
      {
        "tags": null
      }, 
      {
        "faces": null
      }, 
      {
        "Has_info_doc": [
          {
            "info_tpl": "doc ; env ; pull"
          }, 
          {
            "pull_src": null
          }, 
          {
            "Src": [
              {
                "server": "institution"
              }, 
              {
                "place": null
              }, 
              {
                "date": null
              }, 
              {
                "idvs": null
              }, 
              {
                "roles": null
              }, 
              {
                "orgs": "env"
              }
            ]
          }, 
          {
            "Dst": [
              {
                "to_public": "t"
              }
            ]
          }, 
          {
            "Event": [
              {
                "date": "doc"
              }, 
              {
                "time": null
              }, 
              {
                "adr_doc_tsbr_io": "_0000_0000"
              }
            ]
          }
        ]
      }, 
      {
        "Coding": [
          {
            "values": "html"
          }, 
          {
            "tree_odj": "h-li"
          }, 
          {
            "title": 1
          }, 
          {
            "comment": 0
          }, 
          {
            "action_request": null
          }, 
          {
            "noise": 0
          }
        ]
      }, 
      {
        "Licence": [
          {
            "DroitDeRegard": [
              {
                "Licence": "CC-BY-SA-NC"
              }, 
              {
                "Auteur": "Patrick Installé 2013"
              }
            ]
          }
        ]
      }
    ]
  }, 
  {
    "Taxonomy": [
      {
        "rdf": "http://www.w3.org/1999/02/22-rdf-syntax-ns#"
      }, 
      {
        "rdfs": "http://www.w3.org/2000/01/rdf-schema#"
      }, 
      {
        "foaf": "http://xmlns.com/foaf/0.1/"
      }, 
      {
        "bio": "http://purl.org/vocab/bio/0.1/"
      }, 
      {
        "dc": "http://purl.org/dc/terms/"
      }, 
      {
        "lang": "http://purl.org/net/inkel/rdf/schemas/lang/1.1#"
      }, 
      {
        "geo": "http://www.w3.org/2003/01/geo/wgs84_pos#"
      }, 
      {
        "doac": "http://ramonantonio.net/doac/0.1/"
      }, 
      {
        "menow": "http://schema.peoplesdns.com/menow/"
      }, 
      {
        "sioc": "http://rdfs.org/sioc/ns#"
      }, 
      {
        "owl": "http://www.w3.org/2002/07/owl#"
      }, 
      {
        "admin": "http://webns.net/mvcb/"
      }, 
      {
        "rel": "http://purl.org/vocab/relationship/"
      }
    ]
  }
]